{
  "$schema": "http://timetable-registry.amrita.town/v2/schema.json",
  "subjects": {
    "A": {
      "name": "Mathematics for Computing 2",
      "code": "22MAT122",
      "faculty": [
        "Dr. Neetu Srivastava"
      ],
      "shortName": "Math"
    },
    "B": {
      "name": "Object Oriented Programming in Java",
      "code": "22AIE111",
      "faculty": [
        "Dr. Reena Panwar",
        "Dr. Sajitha",
        "Ms. Swetha"
      ],
      "shortName": "Prog"
    },
    "C": {
      "name": "Data Structures & Algorithms 1",
      "code": "22AIE112",
      "faculty": [
        "Dr. Thushara G A",
        "Dr. Radha",
        "Dr. Santhanalaksmi"
      ],
      "shortName": "DS"
    },
    "D": {
      "name": "Elements of Computing Systems 2",
      "code": "22AIE113",
      "faculty": [
        "Mr. Lijin",
        "Dr. Ritesh Raj"
      ],
      "shortName": "ECS"
    },
    "E": {
      "name": "Introduction to Electrical and Electronics Engineering",
      "code": "22AIE114",
      "faculty": [
        "Dr. Sujith Kumar"
      ],
      "shortName": "IEE"
    },
    "F": {
      "name": "User Interface Design",
      "code": "22AIE115",
      "faculty": [
        "Dr. Manju Khanna",
        "Ms. Arya R"
      ],
      "shortName": "UI"
    },
    "G": {
      "name": "Glimpses of Glorious India",
      "code": "22ADM111",
      "faculty": [
        "New Faculty"
      ],
      "shortName": "GGI"
    }
  },
  "config": {},
  "slots": {},
  "schedule": {
    "Monday": [
      "D_LAB",
      "D_LAB",
      "D_LAB",
      "C",
      "B",
      "E_LAB",
      "E_LAB"
    ],
    "Tuesday": [
      "B_LAB",
      "B_LAB",
      "B_LAB",
      "A",
      "C",
      "FREE",
      "FREE"
    ],
    "Wednesday": [
      "F",
      "E",
      "G",
      "D",
      "C",
      "A",
      "B"
    ],
    "Thursday": [
      "B",
      "G",
      "D",
      "C_LAB",
      "C_LAB",
      "A",
      "F"
    ],
    "Friday": [
      "A_LAB",
      "A_LAB",
      "A_LAB",
      "E",
      "FREE",
      "F_LAB",
      "F_LAB"
    ]
  }
}